Metadata-Version: 2.4
Name: py-tggram
Version: 0.1.4
Summary: Elegant, modern and asynchronous Telegram MTProto API framework in Python for users and bots
Project-URL: Homepage, https://kurigram.live
Project-URL: Documentation, https://docs.kurigram.live
Project-URL: Source, https://github.com/Endtrz/py-gram
Project-URL: Issues, https://github.com/Endtrz/py-gram/issues
Project-URL: Community, https://t.me/Endxoz
Author-email: Endtrz <endtrz@gmail.com>
Maintainer: Endtrz
License: LGPL-3.0-or-later
License-File: COPYING
License-File: COPYING.lesser
License-File: NOTICE
Keywords: api,chat,client,library,messenger,mtproto,python,telegram
Classifier: Development Status :: 5 - Production/Stable
Classifier: Intended Audience :: Developers
Classifier: License :: OSI Approved :: GNU Lesser General Public License v3 (LGPLv3)
Classifier: Natural Language :: English
Classifier: Operating System :: OS Independent
Classifier: Programming Language :: Python
Classifier: Programming Language :: Python :: 3
Classifier: Programming Language :: Python :: 3.8
Classifier: Programming Language :: Python :: 3.9
Classifier: Programming Language :: Python :: 3.10
Classifier: Programming Language :: Python :: 3.11
Classifier: Programming Language :: Python :: 3.12
Classifier: Programming Language :: Python :: 3.13
Classifier: Programming Language :: Python :: Implementation :: CPython
Classifier: Programming Language :: Python :: Implementation :: PyPy
Classifier: Topic :: Communications
Classifier: Topic :: Communications :: Chat
Classifier: Topic :: Internet
Classifier: Topic :: Software Development :: Libraries
Classifier: Topic :: Software Development :: Libraries :: Application Frameworks
Classifier: Topic :: Software Development :: Libraries :: Python Modules
Requires-Python: >=3.8
Provides-Extra: dev
Requires-Dist: hatch<=1.7.0; extra == 'dev'
Requires-Dist: keyring<=25.1.0; extra == 'dev'
Requires-Dist: pytest-asyncio<=0.21.1; extra == 'dev'
Requires-Dist: pytest-cov<=4.1.0; extra == 'dev'
Requires-Dist: pytest<=7.4.3; extra == 'dev'
Requires-Dist: twine<=4.0.2; extra == 'dev'
Provides-Extra: docs
Requires-Dist: furo<=2025.7.19; extra == 'docs'
Requires-Dist: pygments<=2.19.2; extra == 'docs'
Requires-Dist: sphinx-autobuild<=2024.10.3; extra == 'docs'
Requires-Dist: sphinx-copybutton<=0.5.2; extra == 'docs'
Requires-Dist: sphinx<=8.2.3; extra == 'docs'
Provides-Extra: fast
Requires-Dist: tgcrypto<=1.2.5; extra == 'fast'
Requires-Dist: uvloop<=0.21.0; (sys_platform == 'darwin' or sys_platform == 'linux') and extra == 'fast'
